redPacket/__init__.py
redPacket/redPacket.py
redPacket-0.1.1.dist-info/LICENSE
redPacket-0.1.1.dist-info/METADATA
redPacket-0.1.1.dist-info/WHEEL
redPacket-0.1.1.dist-info/top_level.txt
redPacket-0.1.1.dist-info/zip-safe
redPacket-0.1.1.dist-info/RECORD
